SNOBOL4python/SNOBOL4functions.py
SNOBOL4python/SNOBOL4patterns.py
SNOBOL4python/__init__.py
SNOBOL4python/deleteme.py
snobol4python-0.4.5.dist-info/licenses/LICENSE
snobol4python-0.4.5.dist-info/METADATA
snobol4python-0.4.5.dist-info/WHEEL
snobol4python-0.4.5.dist-info/top_level.txt
snobol4python-0.4.5.dist-info/RECORD
